{
  "$schema": "http://json-schema.org/schema",
  "type": "object",
  "required": [
    "skipPackageJson",
    "skipInstall",
    "skipNxJson",
    "registerSyncGeneratorGlobally",
    "registerPlugin"
  ],
  "additionalProperties": true,
  "$id": "InitSchema",
  "title": "InitSchema Generator Options",
  "properties": {
    "skipPackageJson": {
      "default": false,
      "type": "boolean"
    },
    "skipInstall": {
      "default": false,
      "type": "boolean"
    },
    "skipNxJson": {
      "default": false,
      "type": "boolean"
    },
    "registerSyncGeneratorGlobally": {
      "default": false,
      "type": "boolean"
    },
    "registerPlugin": {
      "default": false,
      "type": "boolean"
    }
  },
  "description": "Init generator"
}
